nonebot_plugin_beauty_rater-0.1.3.dist-info/METADATA
nonebot_plugin_beauty_rater-0.1.3.dist-info/WHEEL
nonebot_plugin_beauty_rater-0.1.3.dist-info/licenses/LICENSE
nonebot_plugin_beauty_rater/__init__.py
nonebot_plugin_beauty_rater/config.py
nonebot_plugin_beauty_rater/i18n/.config.json
nonebot_plugin_beauty_rater/i18n/.lang.schema.json
nonebot_plugin_beauty_rater/i18n/.template.json
nonebot_plugin_beauty_rater/i18n/.template.schema.json
nonebot_plugin_beauty_rater/i18n/__init__.py
nonebot_plugin_beauty_rater/i18n/en-US.json
nonebot_plugin_beauty_rater/i18n/model.py
nonebot_plugin_beauty_rater/i18n/zh-CN.json
nonebot_plugin_beauty_rater/resources/fonts/simyou.ttf
nonebot_plugin_beauty_rater/utils.py
nonebot_plugin_beauty_rater-0.1.3.dist-info/RECORD
