Metadata-Version: 2.1
Name: nonebot-plugin-beauty-rater
Version: 0.1.3
Summary: NoneBot2 颜值打分插件
Home-page: https://github.com/KomoriDev/nonebot-plugin-beauty-rater
Author-Email: KomoriDev <mute231010@gmail.com>
License: MIT
Project-URL: Homepage, https://github.com/KomoriDev/nonebot-plugin-beauty-rater
Project-URL: Repository, https://github.com/KomoriDev/nonebot-plugin-beauty-rater
Requires-Python: >=3.10
Requires-Dist: nonebot2[fastapi]>=2.3.0
Requires-Dist: nonebot-plugin-alconna>=0.46.4
Requires-Dist: nonebot-plugin-waiter>=0.6.1
Requires-Dist: pillow>=10.3.0
Requires-Dist: httpx>=0.27.0
Requires-Dist: nonebot-adapter-onebot>=2.4.3; extra == "adapters"
Provides-Extra: adapters
